deluge_search-0.1.1.dist-info/dependency_links.txt
deluge_search-0.1.1.dist-info/entry_points.txt
deluge_search-0.1.1.dist-info/METADATA
deluge_search-0.1.1.dist-info/top_level.txt
deluge_search-0.1.1.dist-info/WHEEL
deluge_search/torrent.py
deluge_search/client.py
deluge_search/__init__.py
deluge_search/cli.py
deluge_search/ctx.py
deluge_search/tool.py
deluge_search-0.1.1.dist-info/RECORD